bswitch_python-0.30.0.dist-info/METADATA
bswitch_python-0.30.0.dist-info/WHEEL
libpybswitch.libs/libgcc_s-1e52349c.so.1
libpybswitch/__init__.py
libpybswitch/libpybswitch.cpython-37m-x86_64-linux-gnu.so
bswitch_python-0.30.0.dist-info/RECORD
