Metadata-Version: 2.1
Name: bswitch-python
Version: 0.30.0
